setup.py
neatmartinet/__init__.py
neatmartinet/nmcompare.py
neatmartinet/nmsap.py
neatmartinet/nmstring.py
neatmartinet/nmtable.py
neatmartinet.egg-info/PKG-INFO
neatmartinet.egg-info/SOURCES.txt
neatmartinet.egg-info/dependency_links.txt
neatmartinet.egg-info/not-zip-safe
neatmartinet.egg-info/requires.txt
neatmartinet.egg-info/top_level.txt