Metadata-Version: 1.1
Name: neatmartinet
Version: 0.2.5
Summary: Ad-hoc pandas dataframe and string cleaning functions implemented in unreadable Python.
Home-page: https://github.com/ogierpaul/neatmartinet
Author: Amber Ocelot
Author-email: AmberOcelot@gmail.com
License: na
Download-URL: https://github.com/ogierpaul/neatmartinet.git
Keywords: pandas,data cleaning
Platform: UNKNOWN
Classifier: Programming Language :: Python :: 3
Classifier: Topic :: Scientific/Engineering :: Mathematics
Classifier: Intended Audience :: Developers
Classifier: Topic :: Utilities
